facechain/__init__.py
facechain/inference.py
facechain/merge_lora.py
facechain/train_text_to_image_lora.py
facechain-0.0.1.dev0.dist-info/LICENSE
facechain-0.0.1.dev0.dist-info/METADATA
facechain-0.0.1.dev0.dist-info/WHEEL
facechain-0.0.1.dev0.dist-info/top_level.txt
facechain-0.0.1.dev0.dist-info/RECORD
