Metadata-Version: 2.1
Name: facechain
Version: 0.0.1.dev0
Summary: facechain
Author: Shadow Walker
Keywords: facechain
Classifier: Programming Language :: Python :: 3
Classifier: Programming Language :: Python :: 3.8
Classifier: Programming Language :: Python :: 3.9
Classifier: Programming Language :: Python :: 3.10
License-File: LICENSE
Requires-Dist: accelerate
Requires-Dist: transformers
Requires-Dist: diffusers
Requires-Dist: onnxruntime
Requires-Dist: modelscope
Requires-Dist: Pillow
Requires-Dist: opencv-python
Requires-Dist: torchvision
Requires-Dist: mmdet (==2.26.0)
Requires-Dist: mmengine
Requires-Dist: tensorflow (==2.8.0)
Requires-Dist: numpy (==1.22.0)
Requires-Dist: protobuf (==3.20.1)
Requires-Dist: timm
Requires-Dist: scikit-image
Requires-Dist: gradio
